hanlab/__init__.py
hanlab/cnsi.py
hanlab/hydrationGUI.py
hanlab/odnp.py
hanlab/version.py
unittests/__init__.py
unittests/test_hydration.py
hanlab-0.1.2.dist-info/LICENSE
hanlab-0.1.2.dist-info/METADATA
hanlab-0.1.2.dist-info/WHEEL
hanlab-0.1.2.dist-info/entry_points.txt
hanlab-0.1.2.dist-info/top_level.txt
hanlab-0.1.2.dist-info/RECORD
