Metadata-Version: 2.1
Name: hanlab
Version: 0.1.2
Summary: hanlab - odnp data processing and fitting
Home-page: https://github.com/thcasey3/hanlab
Author: Thomas Casey
License: MIT
Download-URL: https://github.com/thcasey3/hanlab/
Project-URL: Homepage, https://thcasey3.github.io/hanlab/
Project-URL: Documentation, https://thcasey3.github.io/hanlab/
Project-URL: Source, https://github.com/thcasey3/hanlab/
Keywords: dnplab odnp nmr epr dnp
Platform: UNKNOWN
Classifier: Development Status :: 3 - Alpha
Classifier: License :: OSI Approved :: MIT License
Classifier: Programming Language :: Python :: 3
Requires-Python: >=3.6
Requires-Dist: dnplab
Requires-Dist: numpy
Requires-Dist: scipy
Requires-Dist: PyQt5
